[
  {
    "title": "아시아개발은행(ADB), 한국의 디지털‧인공지능 혁신 현장 직접 체험",
    "link": "https://www.msit.go.kr/bbs/view.do?sCode=user&mId=307&mPid=208&pageIndex=1&bbsSeqNo=94&nttSeqNo=3186866&searchOpt=ALL&searchTxt=",
    "category": "기관"
  },
  {
    "title": "AI수석ㆍ국가AI전략위, 시민사회와 함께 AI 정책 방향 모색",
    "link": "https://aikorea.go.kr/web/board/brdDetail.do?menu_cd=000012&num=259",
    "category": "기관"
  },
  {
    "title": "국가AI전략위원회, AI 기본사회 세미나 개최(2.12.(목))",
    "link": "https://aikorea.go.kr/web/board/brdDetail.do?menu_cd=000012&num=258",
    "category": "기관"
  },
  {
    "title": "해군, 부산시와 국방·해양 분야 AI 발전 힘 모은다",
    "link": "https://www.mnd.go.kr/cop/kookbang/kookbangIlboView.do?siteId=mnd&pageIndex=1&findType=&findWord=&categoryCode=dema0005&boardSeq=47624&startDate=&endDate=&id=mnd_020101000000",
    "category": "국방"
  },
  {
    "title": "앤트로픽, ＇클로드 오퍼스 4.6＇의 에이전트 16개 C 컴파일러 개발",
    "link": "https://www.aitimes.com/news/articleView.html?idxno=206600",
    "category": "민간"
  },
  {
    "title": "엔비디아, 불법 복제 도서 AI 학습 반박...안나 아카이브 소송 기각 요청",
    "link": "https://www.aitimes.com/news/articleView.html?idxno=206591",
    "category": "민간"
  },
  {
    "title": "PC 넘어 AI 안경·스마트폰으로...오픈클로, 다양한 장치에 탑재",
    "link": "https://www.aitimes.com/news/articleView.html?idxno=206608",
    "category": "민간"
  },
  {
    "title": "크래프톤, ”피지컬 AI로 게임 AI 확장…＇지니 3＇의 게임 엔진 대체는 시기상조”",
    "link": "https://www.aitimes.com/news/articleView.html?idxno=206604",
    "category": "민간"
  },
  {
    "title": "KAIST-NYU, ‘AI 거버넌스 서밋’ 개최…”고위험 AI 기술 별도 모니터링 필요”",
    "link": "https://www.aitimes.com/news/articleView.html?idxno=206612",
    "category": "기관"
  },
  {
    "title": "KAI-한화에어로스페이스, 전략적 파트너십 체결...〃글로벌 시장 공동 대응〃",
    "link": "https://www.aitimes.com/news/articleView.html?idxno=206601",
    "category": "국방"
  },
  {
    "title": "사우디 106조원 국방 시장 개방·K방산 현지화 전략 정조준",
    "link": "https://www.aitimes.com/news/articleView.html?idxno=206593",
    "category": "국방"
  },
  {
    "title": "선관위 “선거운동에 딥페이크 영상 활용…국내 첫 고발 사례 발생”",
    "link": "https://www.aitimes.com/news/articleView.html?idxno=206597",
    "category": "기관"
  },
  {
    "title": "[양현상 칼럼] 60조 원 캐나다 잠수함 사업, 한국 방산이 마주한 ‘패러다임 전환’의 순간",
    "link": "https://www.aitimes.com/news/articleView.html?idxno=206549",
    "category": "국방"
  },
  {
    "title": "바이트댄스, 영상 AI ＇시댄스 2.0＇ 공개...〃영상 생성 넘어 영화 제작〃",
    "link": "https://www.aitimes.com/news/articleView.html?idxno=206577",
    "category": "민간"
  },
  {
    "title": "MS, 오픈AI ＇프론티어＇ 경계령...〃플랫폼 경쟁력으로 승리해야〃",
    "link": "https://www.aitimes.com/news/articleView.html?idxno=206580",
    "category": "민간"
  },
  {
    "title": "사우디아라비아 WDS 2026을 시작으로  K-방산 세계시장 정조준",
    "link": "https://www.dapa.go.kr/dapa/doc/selectDoc.do?docSeq=58146&menuSeq=3069&bbsSeq=326&currentPageNo=1&recordCountPerPage=10",
    "category": "국방"
  },
  {
    "title": "AI·휴머노이드 판도 바꿀 이차전지 초격차 전략 찾자...화학연 국제포럼 개최",
    "link": "https://www.etnews.com/20260209000395",
    "category": "민간"
  },
  {
    "title": "몰트북·오픈클로가 촉발한 AI 위험성…전문가들 “대비 기회로 삼아야”",
    "link": "https://www.etnews.com/20260209000253",
    "category": "기관"
  },
  {
    "title": "[김형민 변호사의 IT경영법무]〈21〉피지컬 AI 시대의 노사갈등",
    "link": "https://www.etnews.com/20260209000364",
    "category": "민간"
  },
  {
    "title": "[단독] 민·관 AI 네트워크 협의체 ＇AINA＇ MWC26에서 공식 출범",
    "link": "https://www.etnews.com/20260209000299",
    "category": "기관"
  },
  {
    "title": "이찬진 금감원장 “감독 행정도 AI 전환...CAIO 신설해 AX 본궤도”",
    "link": "https://www.etnews.com/20260209000178",
    "category": "기관"
  },
  {
    "title": "＇행동＇ 넘어 ＇영향력＇으로…제4차 AI 정상회의, 16일 인도서 개막",
    "link": "https://www.etnews.com/20260209000274",
    "category": "기관"
  },
  {
    "title": "국산 GPU 인프라·DBMS 결합…티맥스티베로-NHN클라우드, ＇AI 인프라＇ 구축",
    "link": "https://www.etnews.com/20260209000255",
    "category": "민간"
  },
  {
    "title": "한화 방산 3사, WDS 2026 총출동…＇K-방산 수출 패키지＇ 선보인다",
    "link": "https://www.etnews.com/20260209000103",
    "category": "국방"
  },
  {
    "title": "TTA, 국내 AI 표준 56건 ITU에 등재",
    "link": "https://www.etnews.com/20260209000058",
    "category": "기관"
  },
  {
    "title": "기술·신뢰 양 날개 K방산 날아오르다",
    "link": "https://kookbang.dema.mil.kr/newsWeb/20260210/3/ATCE_CTGR_0010050000/view.do;JSESSIONID_kookbnagWEB=1CdB4DYob4qlFZ1ojOo8PAcUCox57FQhJdFdbkAzbD959hp4WRZb!925962759",
    "category": "국방"
  },
  {
    "title": "‘그놈 목소리’ 학습한 AI…실시간 통화 분석해 예방",
    "link": "https://kookbang.dema.mil.kr/newsWeb/20260210/1/ATCE_CTGR_0020020007/view.do;JSESSIONID_kookbnagWEB=1CdB4DYob4qlFZ1ojOo8PAcUCox57FQhJdFdbkAzbD959hp4WRZb!925962759",
    "category": "민간"
  },
  {
    "title": "드론이 열어 준 공간력",
    "link": "https://kookbang.dema.mil.kr/newsWeb/20260210/2/ATCE_CTGR_0050010000/view.do;JSESSIONID_kookbnagWEB=1CdB4DYob4qlFZ1ojOo8PAcUCox57FQhJdFdbkAzbD959hp4WRZb!925962759",
    "category": "국방"
  }
]